dstoolbox/__init__.py
dstoolbox/cluster.py
dstoolbox/pipeline.py
dstoolbox/utils.py
dstoolbox/visualization.py
dstoolbox/data/__init__.py
dstoolbox/data/load.py
dstoolbox/data/tests/__init__.py
dstoolbox/data/tests/test_load.py
dstoolbox/models/__init__.py
dstoolbox/models/text.py
dstoolbox/models/tests/__init__.py
dstoolbox/models/tests/test_text.py
dstoolbox/tests/__init__.py
dstoolbox/tests/test_cluster.py
dstoolbox/tests/test_pipeline.py
dstoolbox/tests/test_utils.py
dstoolbox/transformers/__init__.py
dstoolbox/transformers/casting.py
dstoolbox/transformers/padding.py
dstoolbox/transformers/preprocessing.py
dstoolbox/transformers/slicing.py
dstoolbox/transformers/text.py
dstoolbox/transformers/tests/__init__.py
dstoolbox/transformers/tests/test_casting.py
dstoolbox/transformers/tests/test_padding.py
dstoolbox/transformers/tests/test_preprocessing.py
dstoolbox/transformers/tests/test_slicing.py
dstoolbox/transformers/tests/test_text.py
dstoolbox-0.13.0.dist-info/LICENSE
dstoolbox-0.13.0.dist-info/METADATA
dstoolbox-0.13.0.dist-info/WHEEL
dstoolbox-0.13.0.dist-info/top_level.txt
dstoolbox-0.13.0.dist-info/RECORD
