Metadata-Version: 2.1
Name: dstoolbox
Version: 0.13.0
Summary: Tools that make working with scikit-learn and pandas easier.
Home-page: https://github.com/ottogroup/dstoolbox
Download-URL: https://github.com/ottogroup/dstoolbox/tarball/0.13.0
Author: Otto Group
Author-email: benjamin.bossan@ottogroup.com
License-File: LICENSE
Requires-Dist: numpy >=1.22.3
Requires-Dist: pandas >=1.4.2
Requires-Dist: python-dateutil >=2.8.2
Requires-Dist: pytz >=2022.1
Requires-Dist: scikit-learn >=1.1.0
Requires-Dist: scipy >=1.8.0
Requires-Dist: six >=1.16.0
Provides-Extra: docs
Requires-Dist: Sphinx ; extra == 'docs'
Provides-Extra: testing
Requires-Dist: pytest ; extra == 'testing'
Requires-Dist: pytest-cov ; extra == 'testing'
